geonum/__init__.py
geonum/_init_helpers.py
geonum/_version.py
geonum/atmosphere.py
geonum/elevationprofile.py
geonum/exceptions.py
geonum/geopoint.py
geonum/geosetup.py
geonum/geovector3d.py
geonum/helpers.py
geonum/lineongrid.py
geonum/mapping.py
geonum/plot_helpers.py
geonum/topoaccessbase.py
geonum/topodata.py
geonum/topodataaccess.py
geonum/utils.py
geonum-1.6.0.dist-info/licenses/LICENSE
geonum-1.6.0.dist-info/METADATA
geonum-1.6.0.dist-info/WHEEL
geonum-1.6.0.dist-info/top_level.txt
geonum-1.6.0.dist-info/RECORD
