Metadata-Version: 2.4
Name: geonum
Version: 1.6.0
Summary: Toolbox for 3D geonumerical calculations and atmospheric composition
Author-email: Jonas Gliss <jonasgliss@gmail.com>
License: GPLv3+
Project-URL: Homepage, https://github.com/jgliss/geonum
Project-URL: Documentation, https://geonum.readthedocs.io/en/latest/
Classifier: Development Status :: 5 - Production/Stable
Classifier: Intended Audience :: Science/Research
Classifier: Intended Audience :: Education
Classifier: License :: OSI Approved :: GNU General Public License v3 or later (GPLv3+)
Classifier: Programming Language :: Python :: 3.9
Classifier: Programming Language :: Python :: 3.10
Classifier: Programming Language :: Python :: 3.11
Classifier: Programming Language :: Python :: 3.12
Requires-Python: >=3.9
License-File: LICENSE
Requires-Dist: numpy
Requires-Dist: scipy
Requires-Dist: matplotlib
Requires-Dist: LatLon23
Requires-Dist: SRTM.py
Requires-Dist: cartopy
Provides-Extra: test
Requires-Dist: pytest; extra == "test"
Requires-Dist: netcdf4; extra == "test"
Dynamic: license-file
